{
    "categorys": [
        {
            "id":1,
            "name": "Eyes"
        },
        {
            "id":2,
            "name": "Weight"
        },
        {
            "id":3,
            "name": "Ear"
        },
        {
            "id":4,
            "name": "Blood"
        },
        {
            "id":5,
            "name": "Bones"
        },{
            "id":6,
            "name": "Mood"
        },
        {
            "id":7,
            "name": "Breathe"
        },{
            "id":8,
            "name": "Joints"
        },{
            "id":1,
            "name": "Energy"
        }
    ]
}